mohaliyet/__init__.py
mohaliyet/adder.py
mohaliyet-0.1.dist-info/LICENSE
mohaliyet-0.1.dist-info/METADATA
mohaliyet-0.1.dist-info/WHEEL
mohaliyet-0.1.dist-info/top_level.txt
mohaliyet-0.1.dist-info/RECORD
